expool/__init__.py
expool/execution_pool.py
expool/execution_pool_capped.py
expool/execution_pool_monitored.py
expool/execution_pool_open.py
expool/execution_pool_simple.py
expool/execution_pool_wrap.py
expool-0.1.1.dist-info/LICENSE
expool-0.1.1.dist-info/WHEEL
expool-0.1.1.dist-info/METADATA
expool-0.1.1.dist-info/RECORD
