Metadata-Version: 2.1
Name: expool
Version: 0.1.1
Summary: Simple asynchronous execution pool primitive for Python 3.6+
Home-page: https://github.com/scanfactory/execution-pool
License: MIT
Keywords: utility,asyncio,pool
Author: monomonedula
Author-email: valh@tuta.io
Requires-Python: >=3.6,<4.0
Classifier: Framework :: AsyncIO
Classifier: License :: OSI Approved :: MIT License
Classifier: Programming Language :: Python :: 3
Classifier: Programming Language :: Python :: 3.6
Classifier: Programming Language :: Python :: 3.7
Classifier: Programming Language :: Python :: 3.8
Classifier: Programming Language :: Python :: 3.9
Project-URL: Repository, https://github.com/scanfactory/execution-pool
